__init__.py
preeii/__init__.py
preeii/config.py
preeii/curso.py
preeii/curso_carrera.py
preeii/custom_http_adapter.py
preeii/expediente.py
preeii/funciones_consola.py
preeii/funciones_curso.py
preeii/funciones_expediente.py
preeii/funciones_imprimir.py
preeii/funciones_io.py
preeii/funciones_memory_reader.py
preeii/funciones_menu.py
preeii/funciones_procesamiento_expediente.py
preeii/funciones_semestre.py
preeii/funciones_web_scraping.py
preeii/funciones_xlsxwriter.py
preeii/historial.py
preeii/main.py
preeii/main_listing_parser.py
preeii/semestre.py
preeii/student_parser.py
preeii-1.2025.522.dist-info/licenses/LICENSE
preeii-1.2025.522.dist-info/METADATA
preeii-1.2025.522.dist-info/WHEEL
preeii-1.2025.522.dist-info/top_level.txt
preeii-1.2025.522.dist-info/RECORD
