Metadata-Version: 2.4
Name: preeii
Version: 1.2025.522
Summary: Software de soporte de revisión de pre-matrículas para la escuela de ingeniería industrial
Author-email: Mauricio Andres Zamora Hernandez <mauricio.zamora@gmail.com>
Project-URL: Homepage, https://github.com/mauricio-zamora/preeii
Project-URL: Bug Tracker, https://github.com/mauricio-zamora/preeii/issues
Classifier: Programming Language :: Python :: 3
Classifier: License :: OSI Approved :: MIT License
Classifier: Operating System :: OS Independent
Classifier: Development Status :: 3 - Alpha
Classifier: Environment :: Console
Classifier: Intended Audience :: Education
Classifier: License :: OSI Approved :: MIT License
Classifier: Natural Language :: Spanish
Requires-Python: >=3.10
License-File: LICENSE
Requires-Dist: pyperclip
Requires-Dist: requests
Requires-Dist: termcolor
Requires-Dist: XlsxWriter
Dynamic: license-file
